pyaudioduplexfinder/__init__.py
pyaudioduplexfinder/pyaudioduplexfinder.py
pyaudioduplexfinder/pyauduxfind.py
pyaudioduplexfinder/helper_functions/__init__.py
pyaudioduplexfinder-0.3.3.dist-info/DESCRIPTION.rst
pyaudioduplexfinder-0.3.3.dist-info/entry_points.txt
pyaudioduplexfinder-0.3.3.dist-info/METADATA
pyaudioduplexfinder-0.3.3.dist-info/metadata.json
pyaudioduplexfinder-0.3.3.dist-info/RECORD
pyaudioduplexfinder-0.3.3.dist-info/top_level.txt
pyaudioduplexfinder-0.3.3.dist-info/WHEEL
