Metadata-Version: 2.0
Name: pyaudioduplexfinder
Version: 0.3.3
Summary: Find duplicate in audio files
Home-page: https://pyaudioduplexfinder.b1t.uk
Author: Oskar Malnowicz
Author-email: 8@b1t.uk
License: MIT
Platform: UNKNOWN
Requires-Dist: Click
Requires-Dist: colorama
Requires-Dist: pyyaml
Requires-Dist: pyprind
Requires-Dist: humanfriendly
Requires-Dist: tabulate
Requires-Dist: tqdm
